foliant/preprocessors/testrail/__init__.py
foliant/preprocessors/testrail/testrail.py
foliant/preprocessors/testrail/case_templates/1.j2
foliant/preprocessors/testrail/case_templates/2.j2
foliant/preprocessors/testrail/testrailapi/__init__.py
foliant/preprocessors/testrail/testrailapi/testrailapi.py
foliantcontrib.testrail-1.3.1.dist-info/LICENSE
foliantcontrib.testrail-1.3.1.dist-info/METADATA
foliantcontrib.testrail-1.3.1.dist-info/WHEEL
foliantcontrib.testrail-1.3.1.dist-info/top_level.txt
foliantcontrib.testrail-1.3.1.dist-info/RECORD
