Metadata-Version: 2.1
Name: foliantcontrib.testrail
Version: 1.3.1
Summary: Downloader of test cases from TestRail projects.
Home-page: https://github.com/foliant-docs/foliantcontrib.testrail
Author: Anton Bukhtiyarov
Author-email: apkraft@gmail.com
License: MIT
Platform: any
Classifier: Development Status :: 5 - Production/Stable
Classifier: Environment :: Console
Classifier: Intended Audience :: Developers
Classifier: License :: OSI Approved :: MIT License
Classifier: Operating System :: OS Independent
Classifier: Programming Language :: Python
Classifier: Topic :: Documentation
Classifier: Topic :: Utilities
Requires-Dist: foliant (>=1.0.11)
Requires-Dist: Jinja2
